Celestcoord/CelSphere.py
Celestcoord/InNCon.py
Celestcoord/__init__.py
CelestPlot-0.1.dist-info/METADATA
CelestPlot-0.1.dist-info/WHEEL
CelestPlot-0.1.dist-info/top_level.txt
CelestPlot-0.1.dist-info/RECORD
